imgify/__init__.py
imgify/exceptions.py
imgify/models.py
imgify/client/__init__.py
imgify/client/azure.py
imgify/client/base.py
imgify/client/openai.py
imgify-0.1.0.dist-info/METADATA
imgify-0.1.0.dist-info/WHEEL
imgify-0.1.0.dist-info/top_level.txt
imgify-0.1.0.dist-info/RECORD
