Metadata-Version: 2.4
Name: imgify
Version: 0.1.0
Summary: Async Python wrapper for OpenAI and Azure OpenAI image generation APIs.
Requires-Python: >=3.12
Requires-Dist: openai>=2.15.0
Requires-Dist: pydantic>=2.12.5
Requires-Dist: python-dotenv>=1.2.1
